odoo10_addon_website_form_builder-10.0.1.0.1-py2.7-nspkg.pth
odoo/addons/website_form_builder/README.rst
odoo/addons/website_form_builder/__init__.py
odoo/addons/website_form_builder/__manifest__.py
odoo/addons/website_form_builder/demo/assets.xml
odoo/addons/website_form_builder/demo/ir_model.xml
odoo/addons/website_form_builder/i18n/es.po
odoo/addons/website_form_builder/static/description/icon.png
odoo/addons/website_form_builder/static/description/icon.svg
odoo/addons/website_form_builder/static/src/css/website_form_builder.less
odoo/addons/website_form_builder/static/src/js/snippets.js
odoo/addons/website_form_builder/static/src/js/tour.js
odoo/addons/website_form_builder/static/src/js/widgets.js
odoo/addons/website_form_builder/static/src/xml/snippets.xml
odoo/addons/website_form_builder/static/src/xml/widgets.xml
odoo/addons/website_form_builder/templates/assets.xml
odoo/addons/website_form_builder/templates/snippets.xml
odoo/addons/website_form_builder/tests/__init__.py
odoo/addons/website_form_builder/tests/test_ui.py
odoo/addons/website_form_builder/views/ir_model.xml
odoo10_addon_website_form_builder-10.0.1.0.1.dist-info/DESCRIPTION.rst
odoo10_addon_website_form_builder-10.0.1.0.1.dist-info/METADATA
odoo10_addon_website_form_builder-10.0.1.0.1.dist-info/RECORD
odoo10_addon_website_form_builder-10.0.1.0.1.dist-info/WHEEL
odoo10_addon_website_form_builder-10.0.1.0.1.dist-info/metadata.json
odoo10_addon_website_form_builder-10.0.1.0.1.dist-info/namespace_packages.txt
odoo10_addon_website_form_builder-10.0.1.0.1.dist-info/top_level.txt
